README.md
setup.cfg
setup.py
collibra_classification/__init__.py
collibra_classification/api_client.py
collibra_classification/configuration.py
collibra_classification/exceptions.py
collibra_classification/rest.py
collibra_classification.egg-info/PKG-INFO
collibra_classification.egg-info/SOURCES.txt
collibra_classification.egg-info/dependency_links.txt
collibra_classification.egg-info/requires.txt
collibra_classification.egg-info/top_level.txt
collibra_classification/api/__init__.py
collibra_classification/api/data_classification_api.py
collibra_classification/models/__init__.py
collibra_classification/models/add_classification_match_request.py
collibra_classification/models/add_classification_matches_request.py
collibra_classification/models/add_classification_request.py
collibra_classification/models/change_classification_match_request.py
collibra_classification/models/change_classification_request.py
collibra_classification/models/classification.py
collibra_classification/models/classification_match.py
collibra_classification/models/classify_request.py
collibra_classification/models/find_classification_matches_request.py
collibra_classification/models/find_classifications_request.py
collibra_classification/models/job.py
collibra_classification/models/named_resource_reference_impl.py
collibra_classification/models/paged_response_classification.py
collibra_classification/models/paged_response_classification_match.py
test/test_add_classification_match_request.py
test/test_add_classification_matches_request.py
test/test_add_classification_request.py
test/test_change_classification_match_request.py
test/test_change_classification_request.py
test/test_classification.py
test/test_classification_match.py
test/test_classify_request.py
test/test_data_classification_api.py
test/test_find_classification_matches_request.py
test/test_find_classifications_request.py
test/test_job.py
test/test_named_resource_reference_impl.py
test/test_paged_response_classification.py
test/test_paged_response_classification_match.py